setup.py
ostrich/__init__.py
ostrich/histogram.py
ostrich/stats.py
ostrich/stats_collection.py
ostrich/stats_provider.py
ostrich/time_series_collector.py
ostrich/timing.py
ostrich.egg-info/PKG-INFO
ostrich.egg-info/SOURCES.txt
ostrich.egg-info/dependency_links.txt
ostrich.egg-info/requires.txt
ostrich.egg-info/top_level.txt
ostrich.egg-info/zip-safe
ostrich/test/__init__.py
ostrich/test/unit/__init__.py
ostrich/test/unit/test_stats.py
ostrich/test/unit/test_time_Series_collector.py
ostrich/twisted/__init__.py