Metadata-Version: 1.0
Name: ostrich
Version: 0.3.9
Summary: Python port of the Scala Ostrich library
Home-page: http://github.com/wadey/python-ostrich
Author: Wade Simmons
Author-email: wade@wades.im
License: Apache 2.0
Keywords: ostrich
Platform: UNKNOWN
Classifier: Development Status :: 4 - Beta
Classifier: License :: OSI Approved :: BSD License
Classifier: License :: DFSG approved
Classifier: Intended Audience :: Developers
Classifier: Operating System :: OS Independent
Classifier: Natural Language :: English
Classifier: Programming Language :: Python
Classifier: Programming Language :: Python :: 2
Classifier: Programming Language :: Python :: 2.5
Classifier: Programming Language :: Python :: 2.6
Classifier: Topic :: Utilities
Classifier: Topic :: Software Development :: Libraries
